crypto_dev_signer/__init__.py
crypto_dev_signer/common.py
crypto_dev_signer/error.py
crypto_dev_signer/eth/__init__.py
crypto_dev_signer/eth/transaction.py
crypto_dev_signer/eth/signer/__init__.py
crypto_dev_signer/eth/signer/defaultsigner.py
crypto_dev_signer/eth/web3ext/__init__.py
crypto_dev_signer/eth/web3ext/middleware.py
crypto_dev_signer/keystore/__init__.py
crypto_dev_signer/keystore/interface.py
crypto_dev_signer/keystore/postgres.py
crypto_dev_signer/runnable/signer.py
crypto_dev_signer-0.4.11.dist-info/LICENSE.txt
crypto_dev_signer-0.4.11.dist-info/METADATA
crypto_dev_signer-0.4.11.dist-info/WHEEL
crypto_dev_signer-0.4.11.dist-info/entry_points.txt
crypto_dev_signer-0.4.11.dist-info/top_level.txt
crypto_dev_signer-0.4.11.dist-info/RECORD
