Metadata-Version: 2.1
Name: crypto-dev-signer
Version: 0.4.11
Summary: A signer and keystore daemon and library for cryptocurrency software development
Home-page: https://gitlab.com/nolash/crypto-dev-signer
Author: Louis Holbrook
Author-email: dev@holbrook.no
License: GPLv3
Platform: UNKNOWN
Classifier: Programming Language :: Python :: 3
Classifier: Operating System :: OS Independent
Classifier: Development Status :: 3 - Alpha
Classifier: Intended Audience :: Developers
Classifier: Topic :: Software Development :: Libraries
Classifier: License :: OSI Approved :: GNU General Public License v3 or later (GPLv3+)
Requires-Dist: web3 (==5.12.2)
Requires-Dist: psycopg2 (==2.8.6)
Requires-Dist: cryptography (==3.2.1)
Requires-Dist: eth-keys (==0.3.3)
Requires-Dist: pysha3 (==1.0.2)
Requires-Dist: rlp (==2.0.0a1)
Requires-Dist: json-rpc (==1.13.0)
Requires-Dist: confini (==0.3.5)
Requires-Dist: sqlalchemy (==1.3.20)
